setup.py
pyramid_anthrax/__init__.py
pyramid_anthrax/view.py
pyramid_anthrax.egg-info/PKG-INFO
pyramid_anthrax.egg-info/SOURCES.txt
pyramid_anthrax.egg-info/dependency_links.txt
pyramid_anthrax.egg-info/requires.txt
pyramid_anthrax.egg-info/top_level.txt