Metadata-Version: 1.1
Name: pyramid-anthrax
Version: 0.0.3
Summary: Glue for using anthrax in pyramid projects
Home-page: UNKNOWN
Author: Szymon Pyżalski
Author-email: zefciu <szymon@pythonista.net>
License: BSD
Keywords: forms
Platform: UNKNOWN
Classifier: Development Status :: 1 - Planning
Classifier: License :: OSI Approved :: BSD License
Classifier: Framework :: Pyramid
Classifier: Topic :: Internet :: WWW/HTTP :: Dynamic Content
Classifier: Programming Language :: Python :: 3
Classifier: Programming Language :: Python :: 3.2
